[
  {"Submitted":"2016-09-25 19:39:27 -04:00","Choice":"AAA|BBB|CCC","score":"1514","Submitted Login":"msimpson","Submitted From":"216.40.80.53"},
  {"Submitted":"2016-09-25 19:39:19 -04:00","Choice":"FFF|GGG","score":"500","Submitted Login":"msimpson","Submitted From":"216.40.80.53"},
  {"Submitted":"2016-09-25 19:39:09 -04:00","Choice":"HHH|III|JJJ|KKK","score":"-1","Submitted Login":"msimpson","Submitted From":"216.40.80.53"},
  {"Submitted":"2016-09-25 19:39:15 -04:00","Choice":"LLL","score":"15","Submitted Login":"msimpson","Submitted From":"216.40.80.53"}
]
